pwdgen/__init__.py
pwdgen/command_line.py
pwdgen/eff_wordlist.py
pwdgen/generators.py
pwdgen/rand.py
pwdgen/wordlist.py
pwdgen-3.0.0.dist-info/LICENSE.txt
pwdgen-3.0.0.dist-info/METADATA
pwdgen-3.0.0.dist-info/WHEEL
pwdgen-3.0.0.dist-info/entry_points.txt
pwdgen-3.0.0.dist-info/top_level.txt
pwdgen-3.0.0.dist-info/RECORD
