Metadata-Version: 2.1
Name: pwdgen
Version: 3.0.0
Summary: Quickly generate secure passwords and passphrases.
Home-page: https://github.com/brycedrennan/pwdgen
Author: Bryce Drennan
Author-email: pwdgen@brycedrennan.org
License: MIT
Download-URL: https://github.com/brycedrennan/pwdgen/tarball/3.0.0
Keywords: password,passphrase
Platform: UNKNOWN
Classifier: Programming Language :: Python
Classifier: Programming Language :: Python :: 3
Classifier: Programming Language :: Python :: 3.5
Classifier: Programming Language :: Python :: 3.6
Classifier: Topic :: Software Development :: Libraries :: Python Modules
Classifier: Topic :: Security
Classifier: Topic :: Utilities
Requires-Dist: randomlineaccess (==1.04)
Requires-Dist: requests (>=2.10.0)
